LICENSE
MANIFEST.in
README.md
pyproject.toml
setup.py
dq3d/DualQuaternion.h
dq3d/__init__.py
dq3d/dual_quaternion_py.cc
dq3d/op.py
dq3d/quaternion_plugin.h
dq3d.egg-info/PKG-INFO
dq3d.egg-info/SOURCES.txt
dq3d.egg-info/dependency_links.txt
dq3d.egg-info/not-zip-safe
dq3d.egg-info/requires.txt
dq3d.egg-info/top_level.txt
tests/test_dq3d.py
third_party/eigen/Eigen/CMakeLists.txt
third_party/eigen/Eigen/Cholesky
third_party/eigen/Eigen/CholmodSupport
third_party/eigen/Eigen/Core
third_party/eigen/Eigen/Dense
third_party/eigen/Eigen/Eigen
third_party/eigen/Eigen/Eigenvalues
third_party/eigen/Eigen/Geometry
third_party/eigen/Eigen/Householder
third_party/eigen/Eigen/IterativeLinearSolvers
third_party/eigen/Eigen/Jacobi
third_party/eigen/Eigen/KLUSupport
third_party/eigen/Eigen/LU
third_party/eigen/Eigen/MetisSupport
third_party/eigen/Eigen/OrderingMethods
third_party/eigen/Eigen/PaStiXSupport
third_party/eigen/Eigen/PardisoSupport
third_party/eigen/Eigen/QR
third_party/eigen/Eigen/QtAlignedMalloc
third_party/eigen/Eigen/SPQRSupport
third_party/eigen/Eigen/SVD
third_party/eigen/Eigen/Sparse
third_party/eigen/Eigen/SparseCholesky
third_party/eigen/Eigen/SparseCore
third_party/eigen/Eigen/SparseLU
third_party/eigen/Eigen/SparseQR
third_party/eigen/Eigen/StdDeque
third_party/eigen/Eigen/StdList
third_party/eigen/Eigen/StdVector
third_party/eigen/Eigen/SuperLUSupport
third_party/eigen/Eigen/UmfPackSupport
third_party/eigen/Eigen/src/Cholesky/LDLT.h
third_party/eigen/Eigen/src/Cholesky/LLT.h
third_party/eigen/Eigen/src/Cholesky/LLT_LAPACKE.h
third_party/eigen/Eigen/src/CholmodSupport/CholmodSupport.h
third_party/eigen/Eigen/src/Core/ArithmeticSequence.h
third_party/eigen/Eigen/src/Core/Array.h
third_party/eigen/Eigen/src/Core/ArrayBase.h
third_party/eigen/Eigen/src/Core/ArrayWrapper.h
third_party/eigen/Eigen/src/Core/Assign.h
third_party/eigen/Eigen/src/Core/AssignEvaluator.h
third_party/eigen/Eigen/src/Core/Assign_MKL.h
third_party/eigen/Eigen/src/Core/BandMatrix.h
third_party/eigen/Eigen/src/Core/Block.h
third_party/eigen/Eigen/src/Core/BooleanRedux.h
third_party/eigen/Eigen/src/Core/CommaInitializer.h
