Metadata-Version: 2.4
Name: dq3d
Version: 0.3.8
Summary: Dual Quaternion for 3d transformation
Home-page: https://github.com/neka-nat/dq3d
Author: neka-nat
Author-email: nekanat.stock@gmail.com
License-File: LICENSE
Requires-Dist: pybind11>=2.2
Dynamic: author
Dynamic: author-email
Dynamic: description
Dynamic: description-content-type
Dynamic: home-page
Dynamic: license-file
Dynamic: requires-dist
Dynamic: summary
